backup_to_dropbox/__init__.py
backup_to_dropbox/clients.py
backup_to_dropbox/services.py
backup_to_dropbox-0.2.0.data/scripts/backup-to-dropbox.py
tests/__init__.py
tests/backup_service_test.py
tests/client_test.py
tests/encryption_service_test.py
backup_to_dropbox-0.2.0.dist-info/LICENSE
backup_to_dropbox-0.2.0.dist-info/METADATA
backup_to_dropbox-0.2.0.dist-info/WHEEL
backup_to_dropbox-0.2.0.dist-info/top_level.txt
backup_to_dropbox-0.2.0.dist-info/RECORD
