Metadata-Version: 2.1
Name: backup-to-dropbox
Version: 0.2.0
Summary: Tool to generate backups (tar.gz files) and upload them to Dropbox
Home-page: https://github.com/salessandri/backup-to-dropbox
Author: Santiago Alessandri
Author-email: backup-to-dropbox@salessandri.name
License: UNKNOWN
Keywords: backup dropbox
Platform: UNKNOWN
Classifier: Development Status :: 4 - Beta
Classifier: Topic :: System :: Archiving :: Backup
Classifier: Topic :: Utilities
Classifier: License :: OSI Approved :: MIT License
Requires-Dist: dropbox (==10.1.1)
Requires-Dist: pretty-bad-protocol (==3.1.1)
